vernum/__init__.py
vernum/__main__.py
vernum/command/__init__.py
vernum/command/limit_command.py
vernum/command/max_command.py
vernum/command/next_command.py
vernum/error.py
vernum/scheme/__init__.py
vernum/scheme/major_scheme.py
vernum/scheme/minor_alpha_beta_scheme.py
vernum/scheme/minor_scheme.py
vernum/scheme/patch_hyphen_al_be_scheme.py
vernum/scheme/patch_scheme.py
vernum-7.4.0.dist-info/METADATA
vernum-7.4.0.dist-info/WHEEL
vernum-7.4.0.dist-info/entry_points.txt
vernum-7.4.0.dist-info/licenses/LICENSE
vernum-7.4.0.dist-info/RECORD
