Metadata-Version: 2.4
Name: vernum
Version: 7.4.0
Summary: Generate and process semantic version numbers
License: MIT
License-File: LICENSE
Author: Steampunk Wizard
Author-email: vernum@steamwiz.io
Requires-Python: >=3.11,<4.0
Classifier: License :: OSI Approved :: MIT License
Classifier: Programming Language :: Python :: 3
Classifier: Programming Language :: Python :: 3.11
Classifier: Programming Language :: Python :: 3.12
Classifier: Programming Language :: Python :: 3.13
Classifier: Programming Language :: Python :: 3.14
Requires-Dist: wizlib (>=3.3.8,<3.4.0)
Project-URL: Homepage, https://steamwiz.io
Project-URL: Repository, https://gitlab.com/steamwiz/vernum
